{
  "Argentina, Argentina": [
    -29.5349499,
    -62.2661501
  ],
  "La Argentina, Argentina": [
    -33.5423726,
    -59.3157336
  ],
  "Neuquén, Argentina": [
    -38.8502546,
    -69.832275
  ],
  "Buenos Aires, Argentina": [
    -34.6095579,
    -58.3887904
  ],
  "Estados Unidos, Argentina": [
    -25.7195559,
    -62.652508
  ],
  "Córdoba, Argentina": [
    -31.4166867,
    -64.1834193
  ],
  "Bariloche, Argentina": [
    -41.1334781,
    -71.3101474
  ],
  "Brasil, Argentina": [
    -28.6680373,
    -49.3383467
  ],
  "España, Argentina": [
    -27.4439414,
    -59.0178715
  ],
  "Río Negro, Argentina": [
    -40.4811973,
    -67.6145911
  ],
  "Provincia De Buenos Aires, Argentina": [
    -36.3789925,
    -60.3855889
  ],
  "Israel, Argentina": [
    -31.5536915,
    -68.6158269
  ],
  "Chile, Argentina": [
    -33.0473517,
    -71.4731364
  ],
  "Mendoza, Argentina": [
    -34.5970325,
    -68.7304797
  ],
  "México, Argentina": [
    27.0854542,
    -109.1412408
  ],
  "Gobierno Nacional, Argentina": [
    -31.2467635,
    -59.7498679
  ],
  "La Libertad Avanza, Argentina": [
    -32.9218083,
    -60.8073897
  ],
  "Europa, Argentina": [
    -34.6560444,
    -58.5349753
  ],
  "China, Argentina": [
    -34.5788554,
    -58.4772206
  ],
  "América, Argentina": [
    -35.4891187,
    -62.9756868
  ],
  "Ciudad De Buenos Aires, Argentina": [
    -34.6095579,
    -58.3887904
  ],
  "Viedma, Argentina": [
    -40.8084274,
    -62.994722
  ],
  "Casa Rosada, Argentina": [
    -34.6080692,
    -58.3702762
  ],
  "Vaca Muerta, Argentina": [
    -27.2251995,
    -64.1614471
  ],
  "Uruguay, Argentina": [
    -34.604043,
    -58.3870845
  ],
  "Indec, Argentina": [
    -34.610219,
    -58.37523
  ],
  "Irán, Argentina": [
    -24.8340677,
    -65.3811253
  ],
  "Ucrania, Argentina": [
    -31.4076503,
    -64.1542518
  ],
  "Santa Fe, Argentina": [
    -30.3154739,
    -61.1645076
  ],
  "Provincia, Argentina": [
    -46.7959922,
    -67.9641808
  ],
  "Chubut, Argentina": [
    -43.7128356,
    -68.7461817
  ],
  "Rusia, Argentina": [
    -34.6063102,
    -58.4829826
  ],
  "Gabinete, Argentina": [
    -34.6285857,
    -58.4272769
  ],
  "Misiones, Argentina": [
    -26.737224,
    -54.4315257
  ],
  "Rosario, Argentina": [
    -32.9593609,
    -60.6617024
  ],
  "Francia, Argentina": [
    -33.2825351,
    -66.3408239
  ],
  "Italia, Argentina": [
    43.9593221,
    7.8201585
  ],
  "Tierra Del Fuego, Argentina": [
    -54.3815213,
    -67.5678997
  ],
  "En Estados Unidos, Argentina": [
    null,
    null
  ],
  "Ciudad, Argentina": [
    -34.6095579,
    -58.3887904
  ],
  "La Ley, Argentina": [
    -31.418555,
    -64.1863938
  ],
  "Venezuela, Argentina": [
    -34.6152097,
    -58.404737
  ],
  "Mar Del Plata, Argentina": [
    -37.9976168,
    -57.5482079
  ],
  "Patagonia, Argentina": [
    -51.6538867,
    -69.2921939
  ],
  "Colombia, Argentina": [
    4.9037037,
    -75.5025961
  ],
  "Nueva York, Argentina": [
    -25.2483317,
    -62.769643
  ],
  "Centro, Argentina": [
    -31.5368544,
    -68.5218006
  ],
  "Ushuaia, Argentina": [
    -54.807306,
    -68.3084133
  ],
  "Paraguay, Argentina": [
    -34.58435,
    -58.4246382
  ],
  "La Pampa, Argentina": [
    -37.1789623,
    -65.704912
  ],
  "Salta, Argentina": [
    -25.2269908,
    -64.5911956
  ],
  "Gaza, Argentina": [
    -26.8139976,
    -65.3231471
  ],
  "Fuente, Argentina": [
    -34.6129157,
    -68.330491
  ],
  "Río Grande, Argentina": [
    -53.7858275,
    -67.7018562
  ],
  "Tucumán, Argentina": [
    -27.0448424,
    -65.3657954
  ],
  "Miami, Argentina": [
    -41.1484278,
    -71.267382
  ],
  "Adorni, Argentina": [
    null,
    null
  ],
  "Corrientes, Argentina": [
    -29.0177384,
    -57.8869739
  ],
  "Madrid, Argentina": [
    -34.6340432,
    -58.5276583
  ],
  "Alemania, Argentina": [
    -34.5801199,
    -58.505129
  ],
  "Bolivia, Argentina": [
    -34.5767416,
    -58.505542
  ],
  "Perú, Argentina": [
    -34.6085776,
    -58.3745001
  ],
  "La Plata, Argentina": [
    -34.9206797,
    -57.9537638
  ],
  "Canadá, Argentina": [
    -31.5270494,
    -68.5364956
  ],
  "Washington, Argentina": [
    -33.8723584,
    -64.6884445
  ],
  "Municipio, Argentina": [
    -28.5076818,
    -59.0443876
  ],
  "Los Estados Unidos, Argentina": [
    -34.5766628,
    -58.4187655
  ],
  "Aries, Argentina": [
    -29.461101,
    -66.8652722
  ],
  "Jujuy, Argentina": [
    -23.1546219,
    -66.1110913
  ],
  "Caba, Argentina": [
    -34.6161231,
    -58.4356212
  ],
  "Lla, Argentina": [
    -12.0479852,
    -77.093931
  ],
  "Tauro, Argentina": [
    -29.4582323,
    -66.8700229
  ],
  "Ecuador, Argentina": [
    -2.2350434,
    -79.0899754
  ],
  "San Martín De Los Andes, Argentina": [
    -40.1568791,
    -71.3525588
  ],
  "La Luna, Argentina": [
    -24.3084066,
    -63.5571317
  ],
  "La Bombonera, Argentina": [
    -34.6355171,
    -58.3649163
  ],
  "Tolhuin, Argentina": [
    -54.5113492,
    -67.1954004
  ],
  "Barcelona, Argentina": [
    -34.6602809,
    -58.4384433
  ],
  "París, Argentina": [
    -34.6325444,
    -58.5223153
  ],
  "Provincia De Neuquén, Argentina": [
    -38.8502546,
    -69.832275
  ],
  "Palermo, Argentina": [
    -34.5803362,
    -58.4245236
  ],
  "La Tierra, Argentina": [
    -24.8443001,
    -65.4931042
  ],
  "Londres, Argentina": [
    -27.7126212,
    -67.1355516
  ],
  "San Lorenzo, Argentina": [
    -32.7454865,
    -60.743091
  ],
  "La Rioja, Argentina": [
    -29.7824554,
    -67.1147124
  ],
  "Latinoamérica, Argentina": [
    -30.9907865,
    -64.0906859
  ],
  "Lam, Argentina": [
    -6.7525573,
    -79.8429745
  ],
  "Sigamos, Argentina": [
    null,
    null
  ],
  "Santa Cruz, Argentina": [
    -49.0468648,
    -70.27054
  ],
  "Entre Ríos, Argentina": [
    -32.1290686,
    -59.5077664
  ],
  "Chaco, Argentina": [
    -26.3829647,
    -60.8816092
  ],
  "Posadas, Argentina": [
    -27.3664824,
    -55.894295
  ],
  "Formosa, Argentina": [
    -24.5955306,
    -60.4289718
  ],
  "Florida, Argentina": [
    -34.5322058,
    -58.4937312
  ],
  "Qatar, Argentina": [
    -24.8335499,
    -65.4180888
  ],
  "San Martín, Argentina": [
    -34.5771577,
    -58.5377237
  ],
  "San Juan, Argentina": [
    -30.7054363,
    -69.1988222
  ],
  "Estado Nacional, Argentina": [
    -38.7502818,
    -68.1022921
  ],
  "Japón, Argentina": [
    -24.8342979,
    -65.3807163
  ],
  "Villa La Angostura, Argentina": [
    -40.7620693,
    -71.6472306
  ],
  "Santiago Del Estero, Argentina": [
    -27.6431016,
    -63.5408542
  ],
  "Provincia De Río Negro, Argentina": [
    -40.4811973,
    -67.6145911
  ],
  "Lanús, Argentina": [
    -34.7073871,
    -58.3905998
  ],
  "Reino Unido, Argentina": [
    51.512283,
    -0.1486868
  ],
  "Inglaterra, Argentina": [
    -31.5142821,
    -68.4591808
  ],
  "Roma, Argentina": [
    -31.642912,
    -60.7255422
  ],
  "San Luis, Argentina": [
    -33.8985562,
    -66.0614179
  ],
  "Ee.Uu., Argentina": [
    -34.6071454,
    -58.9708142
  ],
  "Cipolletti, Argentina": [
    -38.931342,
    -67.9905921
  ],
  "Australia, Argentina": [
    -34.6451291,
    -58.3797221
  ],
  "República Argentina, Argentina": [
    -29.5349499,
    -62.2661501
  ],
  "Corte Suprema, Argentina": [
    -34.6029082,
    -58.3844234
  ],
  "Bahía Blanca, Argentina": [
    -38.7176522,
    -62.2654871
  ],
  "El Bolsón, Argentina": [
    -41.9649027,
    -71.5348197
  ],
  "Gobierno De Javier Milei, Argentina": [
    null,
    null
  ],
  "Ciudad De, Argentina": [
    -34.6095579,
    -58.3887904
  ],
  "Ezeiza, Argentina": [
    -34.8168141,
    -58.5474234
  ],
  "Tigre, Argentina": [
    -34.4235341,
    -58.5817628
  ],
  "Franja De Gaza, Argentina": [
    null,
    null
  ],
  "Acá, Argentina": [
    -32.6190045,
    -60.7654858
  ],
  "Ciudad Autónoma De Buenos Aires, Argentina": [
    null,
    null
  ],
  "Catamarca, Argentina": [
    -27.7758659,
    -67.171292
  ],
  "California, Argentina": [
    -31.4510961,
    -64.2055231
  ],
  "Zapala, Argentina": [
    -38.9006215,
    -70.0668573
  ],
  "Provincia De Córdoba, Argentina": [
    -32.022249,
    -63.9698736
  ],
  "Municipalidad, Argentina": [
    -31.6497893,
    -60.7117945
  ],
  "Moscú, Argentina": [
    -28.4467991,
    -65.7192984
  ],
  "Centro Cívico, Argentina": [
    -41.1337056,
    -71.3103263
  ],
  "Sudamérica, Argentina": [
    -31.7323765,
    -60.5114149
  ],
  "Banco Central, Argentina": [
    -34.6048076,
    -58.3727355
  ],
  "Covid-19, Argentina": [
    -24.2428149,
    -65.2624543
  ],
  "Uxp, Argentina": [
    null,
    null
  ],
  "Añelo, Argentina": [
    -38.35428,
    -68.7875804
  ],
  "San Carlos De Bariloche, Argentina": [
    -41.1334781,
    -71.3101474
  ],
  "Río De Janeiro, Argentina": [
    -34.6152413,
    -58.429492
  ],
  "Géminis, Argentina": [
    -38.7112286,
    -62.2677286
  ],
  "Plottier, Argentina": [
    -38.9523098,
    -68.2270197
  ],
  "El Cordillerano, Argentina": [
    -31.5925799,
    -68.577803
  ],
  "Casa Blanca, Argentina": [
    -24.3735601,
    -66.2496185
  ],
  "Malvinas, Argentina": [
    -27.4681694,
    -59.0090906
  ],
  "Poder Judicial, Argentina": [
    -32.895348,
    -68.8445239
  ],
  "Provincia Del Neuquén, Argentina": [
    -38.8502546,
    -69.832275
  ],
  "Hollywood, Argentina": [
    -33.0306859,
    -60.6875762
  ],
  "La Matanza, Argentina": [
    -26.5723825,
    -60.1650583
  ],
  "Centenario, Argentina": [
    -38.8301384,
    -68.1215201
  ],
  "Antártida, Argentina": [
    -27.7994726,
    -64.2725339
  ],
  "Los Ángeles, Argentina": [
    -34.456031,
    -60.178984
  ],
  "Estrecho De Ormuz, Argentina": [
    null,
    null
  ],
  "Eldorado, Argentina": [
    -26.4048555,
    -54.6262079
  ],
  "Cuba, Argentina": [
    -34.5381402,
    -58.4498322
  ],
  "Capital, Argentina": [
    -24.9721002,
    -65.2038658
  ],
  "Monumental, Argentina": [
    -34.5452932,
    -58.4497385
  ],
  "Área Metropolitana De Buenos Aires, Argentina": [
    null,
    null
  ],
  "Mercado Libre, Argentina": [
    -34.5474439,
    -58.4890518
  ],
  "Líbano, Argentina": [
    -37.532088,
    -61.285195
  ],
  "Río Cuarto, Argentina": [
    -33.1237585,
    -64.3489782
  ],
  "Islas Malvinas, Argentina": [
    -32.9013031,
    -60.7783281
  ],
  "Montevideo, Argentina": [
    -24.5662505,
    -62.1510371
  ],
  "Capital Federal, Argentina": [
    -34.6161231,
    -58.4356212
  ],
  "El Salvador, Argentina": [
    -25.063558,
    -65.4376514
  ],
  "Capital Humano, Argentina": [
    -34.9164655,
    -57.9453323
  ],
  "Casa De Gobierno, Argentina": [
    -34.6080692,
    -58.3702762
  ],
  "Meta, Argentina": [
    4.1206507,
    -73.5268805
  ],
  "Sudáfrica, Argentina": [
    -37.9441675,
    -57.5969843
  ],
  "Texas, Argentina": [
    -31.4674893,
    -64.2286101
  ],
  "India, Argentina": [
    -24.8335295,
    -65.3819592
  ],
  "Wall Street, Argentina": [
    -34.5620547,
    -58.4569654
  ],
  "Suiza, Argentina": [
    -27.0578696,
    -55.2421403
  ],
  "Luna, Argentina": [
    -34.5945487,
    -59.11071
  ],
  "Mercado Pago, Argentina": [
    -32.9397509,
    -60.6696598
  ],
  "Marte, Argentina": [
    -34.4570137,
    -58.5351583
  ],
  "Portugal, Argentina": [
    -34.6099085,
    -58.433166
  ],
  "Turquía, Argentina": [
    -34.6559029,
    -58.4131777
  ],
  "China Suárez, Argentina": [
    null,
    null
  ],
  "Países Bajos, Argentina": [
    -37.8822498,
    -67.7905543
  ],
  "Corte Suprema De Justicia, Argentina": [
    -34.6029082,
    -58.3844234
  ],
  "Roca, Argentina": [
    -45.8756699,
    -67.5155969
  ],
  "Unidos, Argentina": [
    -27.0104728,
    -54.465005
  ],
  "Gran Buenos Aires, Argentina": [
    -37.3868819,
    -68.9246464
  ],
  "Educación, Argentina": [
    -24.1984335,
    -65.2883315
  ],
  "Eeuu, Argentina": [
    -27.3634972,
    -55.8893291
  ],
  "Rincón De Los Sauces, Argentina": [
    -37.390188,
    -68.9252566
  ],
  "Asia, Argentina": [
    -34.6369157,
    -58.4403946
  ],
  "Palacio De Hacienda, Argentina": [
    null,
    null
  ],
  "Tesoro, Argentina": [
    -27.0901255,
    -66.1562725
  ],
  "General Roca, Argentina": [
    -39.0268342,
    -67.5754674
  ],
  "Santa Rosa, Argentina": [
    -36.6203503,
    -64.2905765
  ],
  "Morón, Argentina": [
    -34.6510527,
    -58.6217416
  ],
  "Alto Valle, Argentina": [
    -38.9631402,
    -67.8664957
  ],
  "Plaza De Mayo, Argentina": [
    -34.6084453,
    -58.3721787
  ],
  "Escorpio, Argentina": [
    -29.4584361,
    -66.8702891
  ],
  "Llaryora, Argentina": [
    null,
    null
  ],
  "África, Argentina": [
    -31.4277725,
    -64.2628587
  ],
  "Teherán, Argentina": [
    -34.8153681,
    -58.2389287
  ],
  "Movistar Arena, Argentina": [
    -34.5942604,
    -58.4481368
  ],
  "Arabia Saudita, Argentina": [
    -24.833614,
    -65.4136054
  ],
  "Punta Del Este, Argentina": [
    -31.3528815,
    -64.2848307
  ],
  "Nueva Zelanda, Argentina": [
    -31.414658,
    -64.1550038
  ],
  "Wanda Nara, Argentina": [
    null,
    null
  ],
  "Lomas De Zamora, Argentina": [
    -34.7572582,
    -58.4026638
  ],
  "Kiev, Argentina": [
    -34.9045603,
    -57.9633725
  ],
  "De Colombia, Argentina": [
    -34.5919798,
    -58.3814036
  ],
  "Chos Malal, Argentina": [
    -37.3785324,
    -70.2719127
  ],
  "Mercurio, Argentina": [
    -31.4314422,
    -64.2097757
  ],
  "Santiago Del Moro, Argentina": [
    null,
    null
  ],
  "Manchester City, Argentina": [
    null,
    null
  ],
  "Virgo, Argentina": [
    -29.4571127,
    -66.8696304
  ],
  "Mirá, Argentina": [
    -31.9030235,
    -61.2781105
  ],
  "Conurbano, Argentina": [
    -34.4242834,
    -58.5786913
  ],
  "Vaticano, Argentina": [
    -32.9558699,
    -68.8624753
  ],
  "Congreso Nacional, Argentina": [
    -54.8246245,
    -68.3350867
  ],
  "Suecia, Argentina": [
    -34.6437236,
    -58.5009568
  ],
  "Info, Argentina": [
    -32.885071,
    -68.8550303
  ],
  "Ciudad De México, Argentina": [
    19.4556899,
    -99.2065654
  ],
  "Avellaneda, Argentina": [
    -34.6648394,
    -58.3628061
  ],
  "San Francisco, Argentina": [
    -31.4249815,
    -62.0840299
  ],
  "Chicago, Argentina": [
    -34.7578656,
    -58.3614091
  ],
  "Recoleta, Argentina": [
    -34.587358,
    -58.39157
  ],
  "Venus, Argentina": [
    -27.73069,
    -62.4479463
  ],
  "Junín De Los Andes, Argentina": [
    -39.9508663,
    -71.0708883
  ],
  "Egipto, Argentina": [
    -24.8354373,
    -65.3792405
  ],
  "Taiwán, Argentina": [
    null,
    null
  ],
  "Florencia, Argentina": [
    -28.0405521,
    -59.2181955
  ],
  "Canal 9 Norte Misionero, Argentina": [
    null,
    null
  ],
  "Anb, Argentina": [
    null,
    null
  ],
  "Panamá, Argentina": [
    -34.6030656,
    -58.431192
  ],
  "Acuario, Argentina": [
    -28.4717565,
    -65.8218581
  ],
  "Lima, Argentina": [
    -34.6091227,
    -58.3826462
  ],
  "Corte Suprema De Justicia De La Nación, Argentina": [
    null,
    null
  ],
  "Pacífico, Argentina": [
    -38.7106853,
    -62.2865141
  ],
  "Valencia, Argentina": [
    -27.385523,
    -57.7335556
  ],
  "Noticiasnet, Argentina": [
    -40.8087477,
    -62.9901034
  ],
  "Quilmes, Argentina": [
    -34.7244434,
    -58.2588168
  ],
  "Belgrano, Argentina": [
    -31.6376037,
    -60.6870912
  ],
  "Las Grutas, Argentina": [
    -40.9938214,
    -65.476336
  ],
  "Oeste, Argentina": [
    -43.2475106,
    -65.3202119
  ],
  "General, Argentina": [
    -34.5406452,
    -58.4606874
  ],
  "Santiago, Argentina": [
    -27.6431016,
    -63.5408542
  ],
  "Oberá, Argentina": [
    -27.4849798,
    -55.1202965
  ],
  "Retiro, Argentina": [
    -34.5911503,
    -58.3746803
  ],
  "Godoy Cruz, Argentina": [
    -32.9283499,
    -68.9050558
  ],
  "Gendarmería Nacional, Argentina": [
    -42.9048106,
    -71.310569
  ],
  "San Pablo, Argentina": [
    -26.8705501,
    -65.3112549
  ],
  "Kremlin, Argentina": [
    -34.6207349,
    -58.4798227
  ],
  "Central, Argentina": [
    -39.0362504,
    -67.5459813
  ],
  "Unrn, Argentina": [
    -40.8298784,
    -62.9738304
  ],
  "Sur, Argentina": [
    -31.662588,
    -64.4300667
  ],
  "Covid, Argentina": [
    -24.2428149,
    -65.2624543
  ],
  "Sena, Argentina": [
    -26.3697432,
    -60.6105573
  ],
  "Dina Huapi, Argentina": [
    -41.0761031,
    -71.1720318
  ],
  "Barracas Central, Argentina": [
    -34.6475867,
    -58.3967688
  ],
  "Núñez, Argentina": [
    -34.5484856,
    -58.4627415
  ],
  "Guatemala, Argentina": [
    15.0002251,
    -92.0141888
  ],
  "Piscis, Argentina": [
    -29.456492,
    -66.8682117
  ],
  "Siria, Argentina": [
    -34.5692486,
    -60.9390538
  ],
  "General Pico, Argentina": [
    -35.6591085,
    -63.7576103
  ],
  "Beijing, Argentina": [
    -34.5889113,
    -58.3911371
  ],
  "Costa Rica, Argentina": [
    -25.5970478,
    -60.694054
  ],
  "Corea Del Sur, Argentina": [
    37.5361344,
    126.9873598
  ],
  "Comodoro Rivadavia, Argentina": [
    -45.8632024,
    -67.4752615
  ],
  "Puerto Madero, Argentina": [
    -34.6103764,
    -58.3622067
  ],
  "El Reino Unido, Argentina": [
    null,
    null
  ],
  "Sol, Argentina": [
    -37.6751332,
    -59.8189084
  ],
  "Conicet, Argentina": [
    -34.5826124,
    -58.4291436
  ],
  "Gobernador, Argentina": [
    -32.8318687,
    -68.7954466
  ],
  "Parques Nacionales, Argentina": [
    -41.139254,
    -71.3096955
  ],
  "Aluminé, Argentina": [
    -39.2384508,
    -70.9158947
  ],
  "Salud, Argentina": [
    -34.6121936,
    -58.3814863
  ],
  "Las Vegas, Argentina": [
    -31.6761089,
    -60.7932794
  ],
  "Aduana, Argentina": [
    -32.9162662,
    -60.7716457
  ],
  "Junín, Argentina": [
    -34.5934412,
    -60.9461678
  ],
  "Aeroparque, Argentina": [
    -34.5594554,
    -58.4143637
  ],
  "Provincia De Santa Fe, Argentina": [
    -30.3154739,
    -61.1645076
  ],
  "Caracas, Argentina": [
    -34.5760901,
    -58.5008146
  ],
  "Gran Bretaña, Argentina": [
    -31.4288042,
    -64.5113544
  ],
  "Sagitario, Argentina": [
    -36.2743435,
    -62.9322728
  ],
  "Talleres, Argentina": [
    -34.5766826,
    -60.9438732
  ],
  "San Isidro, Argentina": [
    -34.4739792,
    -58.5264866
  ],
  "Plaza Huincul, Argentina": [
    -38.9304191,
    -69.200246
  ],
  "Norte, Argentina": [
    -28.4431336,
    -65.7742935
  ],
  "Teatro Colón, Argentina": [
    -34.6010855,
    -58.3831869
  ],
  "San Antonio Oeste, Argentina": [
    -40.7302125,
    -64.9389955
  ],
  "Tandil, Argentina": [
    -37.3282887,
    -59.1356957
  ],
  "Ministro Del Interior, Argentina": [
    null,
    null
  ],
  "Patagones, Argentina": [
    -34.6373248,
    -58.4002814
  ],
  "Bélgica, Argentina": [
    -34.6036934,
    -58.4776921
  ],
  "Gobierno Argentino, Argentina": [
    -38.9513794,
    -68.0636767
  ],
  "Paraná, Argentina": [
    -27.4210173,
    -56.6011693
  ],
  "Caribe, Argentina": [
    -37.9776195,
    -57.6251779
  ],
  "Capricornio, Argentina": [
    -31.3604533,
    -58.0509746
  ],
  "La Rural, Argentina": [
    -33.9028387,
    -60.5335842
  ],
  "Costa Atlántica, Argentina": [
    -45.8133548,
    -67.4352105
  ],
  "Houston, Argentina": [
    null,
    null
  ],
  "Hospital Italiano, Argentina": [
    -34.6078588,
    -58.4236777
  ],
  "Bogotá, Argentina": [
    -34.6321142,
    -58.4872898
  ],
  "Atlántico, Argentina": [
    -46.4685411,
    -67.5169178
  ],
  "Indiana, Argentina": [
    -54.347025,
    -67.422838
  ],
  "Galicia, Argentina": [
    -34.5837044,
    -58.4033154
  ],
  "Liverpool, Argentina": [
    -34.5827482,
    -58.4822684
  ],
  "Noticias Argentinas, Argentina": [
    -33.6751142,
    -65.4631811
  ],
  "Pilar, Argentina": [
    -34.4570918,
    -58.9141609
  ],
  "Recién, Argentina": [
    null,
    null
  ],
  "City, Argentina": [
    -34.5588324,
    -58.4591794
  ],
  "Dinamarca, Argentina": [
    -34.609682,
    -58.4520658
  ],
  "Occidente, Argentina": [
    5.7796133,
    -74.1602698
  ],
  "Colón, Argentina": [
    -32.2182804,
    -58.1356171
  ],
  "Expoagro, Argentina": [
    null,
    null
  ],
  "Parque Nacional Nahuel Huapi, Argentina": [
    -40.872513,
    -71.4684593
  ],
  "Argentinos, Argentina": [
    -34.6389831,
    -58.3613682
  ],
  "Municipalidad De Ushuaia, Argentina": [
    -54.8140946,
    -68.3362999
  ],
  "Leo, Argentina": [
    -34.6434236,
    -58.50359
  ],
  "Gobierno De Río Negro, Argentina": [
    -40.8093554,
    -62.9954495
  ],
  "Villa Gesell, Argentina": [
    -37.2556627,
    -56.9679411
  ],
  "Estadio Monumental, Argentina": [
    -34.5452932,
    -58.4497385
  ],
  "Las Heras, Argentina": [
    -34.5875522,
    -58.3972196
  ],
  "Concejo, Argentina": [
    -34.6095411,
    -58.3745037
  ],
  "Estado., Argentina": [
    -34.6100671,
    -58.3676496
  ],
  "Cáncer, Argentina": [
    -40.81372,
    -63.0015519
  ],
  "Municipio De Río Grande, Argentina": [
    -53.7858275,
    -67.7018562
  ],
  "Concejo Deliberante, Argentina": [
    -34.6095411,
    -58.3745037
  ],
  "Grecia, Argentina": [
    -34.5401667,
    -58.467999
  ],
  "Sevilla, Argentina": [
    -38.7017971,
    -62.2933059
  ],
  "Santiago De Chile, Argentina": [
    -34.6430704,
    -58.5174459
  ],
  "Cerro Catedral, Argentina": [
    -33.3135822,
    -69.9828887
  ],
  "Ituzaingó, Argentina": [
    -34.6583293,
    -58.6671441
  ],
  "Resistencia, Argentina": [
    -27.6048829,
    -59.1932003
  ],
  "Jefatura De Gabinete, Argentina": [
    -38.9515656,
    -68.0640856
  ],
  "Chelsea, Argentina": [
    -39.027655,
    -67.571855
  ],
  "Neuquén.-, Argentina": [
    -38.8502546,
    -69.832275
  ],
  "Bruselas, Argentina": [
    -34.6261594,
    -58.5235633
  ],
  "Rafah, Argentina": [
    null,
    null
  ],
  "Provincia De Misiones, Argentina": [
    -26.737224,
    -54.4315257
  ],
  "Parlamento, Argentina": [
    null,
    null
  ],
  "Rosario Central, Argentina": [
    -32.9055953,
    -60.6803375
  ],
  "Pinamar, Argentina": [
    -37.1099492,
    -56.8539007
  ],
  "San Nicolás, Argentina": [
    -33.3277089,
    -60.2165909
  ],
  "Noruega, Argentina": [
    -34.6116435,
    -58.4955603
  ],
  "Vialidad Nacional, Argentina": [
    -33.2878089,
    -66.3183197
  ],
  "La Paz, Argentina": [
    -30.7422896,
    -59.6439325
  ],
  "Feria Internacional Del Libro De Buenos Aires, Argentina": [
    null,
    null
  ],
  "Esquel, Argentina": [
    -42.9173055,
    -71.3216508
  ],
  "Cuyo, Argentina": [
    -34.6580875,
    -58.4803816
  ],
  "Puerto Iguazú, Argentina": [
    -25.6107508,
    -54.5764199
  ],
  "Ushuaia.-, Argentina": [
    -54.807306,
    -68.3084133
  ],
  "Cámara Baja, Argentina": [
    null,
    null
  ],
  "Caballito, Argentina": [
    -34.6205897,
    -58.4413922
  ],
  "Villa Regina, Argentina": [
    -39.0987435,
    -67.0852996
  ],
  "Municipalidad De Neuquén, Argentina": [
    -38.93322,
    -68.1175746
  ],
  "Davos, Argentina": [
    -30.9749332,
    -64.1053381
  ],
  "Sierra Grande, Argentina": [
    -41.605351,
    -65.3568775
  ],
  "Polonia, Argentina": [
    -26.4067458,
    -54.6221207
  ],
  "Austria, Argentina": [
    -34.5876134,
    -58.4034767
  ],
  "Feria Del Libro, Argentina": [
    -26.8272467,
    -65.2054232
  ],
  "Sumate, Argentina": [
    null,
    null
  ],
  "Noa, Argentina": [
    -32.90002,
    -68.8296139
  ],
  "Berlín, Argentina": [
    -32.6382178,
    -70.0214276
  ],
  "Saturno, Argentina": [
    -36.916221,
    -62.6804394
  ],
  "Obelisco, Argentina": [
    -34.6037093,
    -58.3816296
  ],
  "Central Córdoba, Argentina": [
    -31.2573191,
    -61.4798914
  ],
  "Georgia, Argentina": [
    -31.4863959,
    -64.2378562
  ],
  "América Del Sur, Argentina": [
    -31.4830653,
    -64.2267055
  ],
  "Irlanda, Argentina": [
    -34.541728,
    -58.464904
  ],
  "Libra, Argentina": [
    -41.1238171,
    -71.3970565
  ],
  "Tres Arroyos, Argentina": [
    -38.3770014,
    -60.2755685
  ],
  "Rivadavia, Argentina": [
    -31.5465955,
    -68.6505443
  ],
  "Anses, Argentina": [
    -37.9866593,
    -57.5702922
  ],
  "Federal, Argentina": [
    -30.9558743,
    -58.7797943
  ],
  "Río Colorado, Argentina": [
    -38.7312132,
    -66.2069607
  ],
  "Rio Negro, Argentina": [
    -40.4811973,
    -67.6145911
  ],
  "Cataluña, Argentina": [
    -31.4348831,
    -64.1540506
  ],
  "Incaa, Argentina": [
    -34.6088882,
    -58.3896252
  ],
  "Puerto Madryn, Argentina": [
    -42.7673414,
    -65.0365942
  ],
  "Libertad, Argentina": [
    -34.7003704,
    -58.6834869
  ],
  "Maracaná, Argentina": [
    -27.3012376,
    -54.1935963
  ],
  "Jxc, Argentina": [
    null,
    null
  ],
  "Barracas, Argentina": [
    -34.6452854,
    -58.3875619
  ],
  "Río Neuquén, Argentina": [
    -37.9685333,
    -69.795589
  ],
  "Dallas, Argentina": [
    -31.4708038,
    -64.2315907
  ],
  "Merlo, Argentina": [
    -34.6604988,
    -58.7321695
  ],
  "Pronóstico, Argentina": [
    null,
    null
  ],
  "Emiratos Árabes Unidos, Argentina": [
    -24.8342256,
    -65.413009
  ],
  "Guayaquil, Argentina": [
    -34.6207403,
    -58.4362204
  ],
  "Prefectura Naval Argentina, Argentina": [
    -37.9815532,
    -57.5842038
  ],
  "El Niño, Argentina": [
    -31.3917299,
    -64.1337503
  ],
  "Gobierno Provincial, Argentina": [
    -27.3651736,
    -55.8939918
  ],
  "Gobierno De La Provincia, Argentina": [
    -31.2467635,
    -59.7498679
  ],
  "La Patagonia, Argentina": [
    -38.5173056,
    -69.7255898
  ],
  "Islas Del Atlántico Sur, Argentina": [
    -31.3301662,
    -64.2404427
  ],
  "Transporte, Argentina": [
    -31.5983025,
    -60.6961911
  ],
  "Río De La Plata, Argentina": [
    -28.6177672,
    -65.5094398
  ],
  "Necochea, Argentina": [
    -38.5545494,
    -58.7392624
  ],
  "Villa Mascardi, Argentina": [
    -41.3504752,
    -71.5106159
  ],
  "Justicia Federal, Argentina": [
    -40.8087714,
    -62.9931968
  ],
  "Asunción, Argentina": [
    -27.4479463,
    -58.970579
  ],
  "Virginia, Argentina": [
    -30.7395488,
    -61.3402394
  ],
  "Emerenciano Sena, Argentina": [
    null,
    null
  ],
  "Júpiter, Argentina": [
    -34.4369507,
    -58.727467
  ],
  "Tailandia, Argentina": [
    -46.4284831,
    -67.5349528
  ],
  "Talleres De Córdoba, Argentina": [
    -31.3936035,
    -64.1665003
  ],
  "Luna Park, Argentina": [
    -34.6024261,
    -58.3686914
  ],
  "Hotel Hilton, Argentina": [
    -34.4333223,
    -58.9747345
  ],
  "El Vaticano, Argentina": [
    -31.4050091,
    -64.5023191
  ],
  "Patagonia Argentina, Argentina": [
    -40.7999494,
    -63.0003119
  ],
  "Atlántico Sur, Argentina": [
    -27.4332797,
    -58.976193
  ],
  "Palestina, Argentina": [
    -31.3995306,
    -64.1947608
  ],
  "Corea Del Norte, Argentina": [
    39.0317271,
    125.7358472
  ],
  "Plutón, Argentina": [
    -31.7058433,
    -64.4261372
  ],
  "Banco Provincia, Argentina": [
    -34.2441423,
    -59.4742956
  ],
  "Tokio, Argentina": [
    -34.6129818,
    -58.491271
  ],
  "El Sol, Argentina": [
    -36.7603082,
    -59.8524403
  ],
  "Cabo Verde, Argentina": [
    -27.3805897,
    -55.9098304
  ],
  "Este, Argentina": [
    -34.652821,
    -59.424042
  ],
  "Alem, Argentina": [
    -53.7663805,
    -67.7164716
  ],
  "Pensilvania, Argentina": [
    -31.4746872,
    -64.2355768
  ],
  "Medellín, Argentina": [
    -28.651611,
    -63.7846096
  ],
  "Senillosa, Argentina": [
    -39.0134511,
    -68.4267867
  ],
  "Estado Provincial, Argentina": [
    -34.6093463,
    -58.3761415
  ],
  "Chascomús, Argentina": [
    -35.5786869,
    -58.0138252
  ],
  "Foto, Argentina": [
    -34.640386,
    -58.5266683
  ],
  "Luján, Argentina": [
    -34.5661734,
    -59.1152598
  ],
  "Aten, Argentina": [
    -38.8291183,
    -68.1363078
  ],
  "Pakistán, Argentina": [
    -34.5640968,
    -58.4234137
  ],
  "Quinta De Olivos, Argentina": [
    -34.5151079,
    -58.4831004
  ],
  "Mercadona, Argentina": [
    36.6841796,
    -4.4575963
  ],
  "Catedral, Argentina": [
    -34.60757,
    -58.3742905
  ],
  "Cinco Saltos, Argentina": [
    -38.8275693,
    -68.0661786
  ],
  "Quito, Argentina": [
    -34.617056,
    -58.4265965
  ],
  "Ministro De Economía, Argentina": [
    null,
    null
  ],
  "Trelew, Argentina": [
    -43.2531242,
    -65.3094407
  ],
  "Río Gallegos, Argentina": [
    -51.6268852,
    -69.105804
  ],
  "Provincia De Mendoza, Argentina": [
    -34.5970325,
    -68.7304797
  ],
  "Beirut, Argentina": [
    -34.8123839,
    -58.249729
  ],
  "Maipú, Argentina": [
    -32.9846171,
    -68.7882043
  ],
  "Unco, Argentina": [
    -38.9394882,
    -68.0503365
  ],
  "Confluencia, Argentina": [
    -38.9625705,
    -68.0313581
  ],
  "Zona A, Argentina": [
    -31.5920816,
    -64.3498546
  ],
  "Olivos, Argentina": [
    -34.5110708,
    -58.4901197
  ],
  "Manhattan, Argentina": [
    -34.6085926,
    -58.4058773
  ],
  "Chapelco, Argentina": [
    -40.2271964,
    -71.2547613
  ],
  "Tren Patagónico, Argentina": [
    -41.1308315,
    -71.2794813
  ],
  "Reserva Federal, Argentina": [
    -27.3965483,
    -55.649989
  ],
  "Urano, Argentina": [
    -29.4007971,
    -66.7859216
  ],
  "La Ribera, Argentina": [
    -39.0794914,
    -67.5743045
  ],
  "Amia, Argentina": [
    -38.9711526,
    -67.8201541
  ],
  "Mar Negro, Argentina": [
    -24.8302128,
    -65.4145587
  ],
  "Falta, Argentina": [
    -34.0861717,
    -59.0323773
  ],
  "Gobierno De La Ciudad, Argentina": [
    -31.6581416,
    -60.7107039
  ],
  "Villa María, Argentina": [
    -32.4106245,
    -63.2435809
  ],
  "La Boca, Argentina": [
    -34.6335103,
    -58.3590424
  ],
  "Puerto Rico, Argentina": [
    -26.8167893,
    -55.0266912
  ],
  "Villa Pehuenia, Argentina": [
    -38.8813069,
    -71.1740024
  ],
  "Jerusalén, Argentina": [
    -31.5866538,
    -68.5614775
  ],
  "Cordillera De Los Andes, Argentina": [
    -31.5046017,
    -68.4853983
  ],
  "Boedo, Argentina": [
    -34.6254799,
    -58.4161163
  ],
  "Vista Alegre, Argentina": [
    -38.7177463,
    -62.3129938
  ],
  "San Pedro, Argentina": [
    -33.6760716,
    -59.6629342
  ],
  "Sinaloa, Argentina": [
    24.7775362,
    -107.4056855
  ],
  "Parque Nacional Los Alerces, Argentina": [
    -42.842119,
    -71.8763961
  ],
  "San Patricio Del Chañar, Argentina": [
    -38.6312548,
    -68.2971527
  ],
  "Finlandia, Argentina": [
    -34.6532829,
    -58.5156011
  ],
  "Catriel, Argentina": [
    -37.8792422,
    -67.7919078
  ],
  "Estambul, Argentina": [
    -36.6208257,
    -64.2858519
  ],
  "Tenerife, Argentina": [
    -31.4614644,
    -64.206782
  ],
  "Honduras, Argentina": [
    -34.5931134,
    -58.4239945
  ],
  "Norteamérica, Argentina": [
    -34.6317396,
    -58.5671025
  ],
  "Allen, Argentina": [
    -38.9795062,
    -67.8280092
  ],
  "Cisjordania, Argentina": [
    null,
    null
  ],
  "Río Paraná, Argentina": [
    -27.4210173,
    -56.6011693
  ],
  "Na).-, Argentina": [
    -28.6680373,
    -49.3383467
  ],
  "Singapur, Argentina": [
    -32.9361957,
    -60.8024185
  ],
  "Moreno, Argentina": [
    -34.6396556,
    -58.7898326
  ],
  "Móvil, Argentina": [
    -37.5086349,
    -61.8509425
  ],
  "República Dominicana, Argentina": [
    -34.5909094,
    -58.4136448
  ],
  "Manzana, Argentina": [
    -34.610524,
    -58.3747376
  ],
  "Mar Rojo, Argentina": [
    -24.8275948,
    -65.425639
  ],
  "Fit, Argentina": [
    -34.5956906,
    -58.3943958
  ],
  "Jordania, Argentina": [
    -24.834016,
    -65.4147766
  ],
  "Policía De Río Negro, Argentina": [
    -41.12207,
    -71.2355667
  ],
  "Damasco, Argentina": [
    -31.5886194,
    -68.5621005
  ],
  "Provincia De Tierra Del Fuego, Argentina": [
    -34.5947225,
    -58.3816995
  ],
  "Nueva Jersey, Argentina": [
    -31.4678412,
    -64.2284524
  ],
  "Legislatura De Río Negro, Argentina": [
    -37.8842818,
    -67.8009837
  ],
  "Lago Nahuel Huapi, Argentina": [
    -40.9202836,
    -71.520956
  ],
  "Mercado De Pases, Argentina": [
    null,
    null
  ],
  "Choel, Argentina": [
    -39.2932355,
    -65.6615828
  ],
  "Gobierno De La Ciudad De Buenos Aires, Argentina": [
    -34.6399289,
    -58.4059321
  ],
  "Ministro De Justicia, Argentina": [
    null,
    null
  ],
  "Escocia, Argentina": [
    -32.9261081,
    -60.7314616
  ],
  "Porto Alegre, Argentina": [
    -34.9334429,
    -58.6152682
  ],
  "Tel Aviv, Argentina": [
    -34.6404466,
    -58.7119916
  ],
  "Indonesia, Argentina": [
    -27.4600221,
    -58.7965525
  ],
  "Unter, Argentina": [
    31.951381,
    34.8609717
  ],
  "Bielorrusia, Argentina": [
    null,
    null
  ],
  "Gas Natural Licuado, Argentina": [
    null,
    null
  ],
  "Wanda, Argentina": [
    -25.9693011,
    -54.5696922
  ],
  "Recorrido, Argentina": [
    -30.0855026,
    -67.9235122
  ],
  "Ministro De Salud, Argentina": [
    null,
    null
  ],
  "Estado Argentino, Argentina": [
    -49.3288963,
    -72.8895536
  ],
  "Arroyito, Argentina": [
    -31.4192409,
    -63.0509405
  ],
  "Atlanta, Argentina": [
    -34.5942673,
    -58.4486027
  ]
}